sunbasket/__init__.py
sunbasket/data.py
sunbasket/handler.py
sunbasket/sunbasket_config.yaml
sunbasket/test/test_data.py
sunbasket/test/test_handler.py
sunbasket/test/test_sunbasket.py
sunbasket/test/__pycache__/test_data.cpython-310.pyc
sunbasket/test/__pycache__/test_handler.cpython-310.pyc
sunbasket/test/__pycache__/test_sunbasket.cpython-310.pyc
shihua_sunbasket-0.1.1.dist-info/LICENSE
shihua_sunbasket-0.1.1.dist-info/METADATA
shihua_sunbasket-0.1.1.dist-info/WHEEL
shihua_sunbasket-0.1.1.dist-info/top_level.txt
shihua_sunbasket-0.1.1.dist-info/RECORD
